{
  "products": [
    {
      "id": "todo_list",
      "name": "To-Do List",
      "tier": 1,
      "sector": "CONCEPT",
      "cost_software": 4,
      "cost_hardware": 0,
      "revenue": 1,
      "valuation": 1,
      "maint_software": 1,
      "maint_hardware": 0,
      "requires": [],
      "provides": "APP"
    },
    {
      "id": "flashlight_app",
      "name": "Flashlight App",
      "tier": 1,
      "sector": "CONCEPT",
      "cost_software": 4,
      "cost_hardware": 0,
      "revenue": 1,
      "valuation": 1,
      "maint_software": 1,
      "maint_hardware": 0,
      "requires": [],
      "provides": "APP"
    },
    {
      "id": "basic_website",
      "name": "Basic Website",
      "tier": 1,
      "sector": "CONCEPT",
      "cost_software": 4,
      "cost_hardware": 0,
      "revenue": 1,
      "valuation": 1,
      "maint_software": 1,
      "maint_hardware": 0,
      "requires": [],
      "provides": "PLATFORM"
    },
    {
      "id": "usb_gadget",
      "name": "USB Gadget",
      "tier": 1,
      "sector": "CONCEPT",
      "cost_software": 4,
      "cost_hardware": 0,
      "revenue": 1,
      "valuation": 1,
      "maint_software": 1,
      "maint_hardware": 0,
      "requires": [],
      "provides": "DEVICE"
    },
    {
      "id": "dating_app",
      "name": "Dating App",
      "tier": 1,
      "sector": "CONSUMER",
      "cost_software": 6,
      "cost_hardware": 0,
      "revenue": 1,
      "valuation": 5,
      "maint_software": 1,
      "maint_hardware": 0,
      "requires": [],
      "provides": "SOCIAL"
    },
    {
      "id": "viral_video_app",
      "name": "Viral Video App",
      "tier": 1,
      "sector": "CONSUMER",
      "cost_software": 6,
      "cost_hardware": 0,
      "revenue": 2,
      "valuation": 3,
      "maint_software": 1,
      "maint_hardware": 0,
      "requires": [],
      "provides": "SOCIAL"
    },
    {
      "id": "messaging_app",
      "name": "Messaging App",
      "tier": 1,
      "sector": "CONSUMER",
      "cost_software": 4,
      "cost_hardware": 0,
      "revenue": 1,
      "valuation": 2,
      "maint_software": 1,
      "maint_hardware": 0,
      "requires": [],
      "provides": "SOCIAL"
    },
    {
      "id": "mobile_wallet",
      "name": "Mobile Wallet",
      "tier": 1,
      "sector": "FINTECH",
      "cost_software": 4,
      "cost_hardware": 0,
      "revenue": 2,
      "valuation": 2,
      "maint_software": 1,
      "maint_hardware": 0,
      "requires": [],
      "provides": "COMMERCE"
    },
    {
      "id": "payment_gateway",
      "name": "Payment Gateway",
      "tier": 1,
      "sector": "FINTECH",
      "cost_software": 6,
      "cost_hardware": 0,
      "revenue": 3,
      "valuation": 2,
      "maint_software": 1,
      "maint_hardware": 0,
      "requires": [],
      "provides": "COMMERCE"
    },
    {
      "id": "trading_bot",
      "name": "Trading Bot",
      "tier": 1,
      "sector": "FINTECH",
      "cost_software": 6,
      "cost_hardware": 0,
      "revenue": 4,
      "valuation": 1,
      "maint_software": 2,
      "maint_hardware": 0,
      "requires": [],
      "provides": "COMMERCE"
    },
    {
      "id": "smart_thermostat",
      "name": "Smart Thermostat",
      "tier": 1,
      "sector": "DEEP_TECH",
      "cost_software": 2,
      "cost_hardware": 4,
      "revenue": 2,
      "valuation": 3,
      "maint_software": 0,
      "maint_hardware": 1,
      "requires": [],
      "provides": "IOT"
    },
    {
      "id": "fitness_wearable",
      "name": "Fitness Wearable",
      "tier": 1,
      "sector": "DEEP_TECH",
      "cost_software": 2,
      "cost_hardware": 4,
      "revenue": 2,
      "valuation": 3,
      "maint_software": 0,
      "maint_hardware": 1,
      "requires": [],
      "provides": "IOT"
    },
    {
      "id": "smart_lock",
      "name": "Smart Lock",
      "tier": 1,
      "sector": "DEEP_TECH",
      "cost_software": 1,
      "cost_hardware": 5,
      "revenue": 2,
      "valuation": 3,
      "maint_software": 0,
      "maint_hardware": 1,
      "requires": [],
      "provides": "IOT"
    },
    {
      "id": "health_tracker",
      "name": "Health Tracker",
      "tier": 1,
      "sector": "LIFE_SCI",
      "cost_software": 4,
      "cost_hardware": 0,
      "revenue": 1,
      "valuation": 2,
      "maint_software": 1,
      "maint_hardware": 0,
      "requires": [],
      "provides": "DATA"
    },
    {
      "id": "genetics_kit",
      "name": "Genetics Kit",
      "tier": 1,
      "sector": "LIFE_SCI",
      "cost_software": 0,
      "cost_hardware": 8,
      "revenue": 3,
      "valuation": 4,
      "maint_software": 0,
      "maint_hardware": 1,
      "requires": [],
      "provides": "DATA"
    },
    {
      "id": "telehealth_platform",
      "name": "Telehealth Platform",
      "tier": 1,
      "sector": "LIFE_SCI",
      "cost_software": 6,
      "cost_hardware": 0,
      "revenue": 2,
      "valuation": 3,
      "maint_software": 1,
      "maint_hardware": 0,
      "requires": [],
      "provides": "DATA"
    },
    {
      "id": "tech_blog",
      "name": "Tech Blog",
      "tier": 1,
      "sector": "INFRA",
      "cost_software": 4,
      "cost_hardware": 0,
      "revenue": 1,
      "valuation": 1,
      "maint_software": 1,
      "maint_hardware": 0,
      "requires": [],
      "provides": "PLATFORM"
    },
    {
      "id": "cloud_storage",
      "name": "Cloud Storage",
      "tier": 1,
      "sector": "INFRA",
      "cost_software": 4,
      "cost_hardware": 4,
      "revenue": 3,
      "valuation": 2,
      "maint_software": 0,
      "maint_hardware": 1,
      "requires": [],
      "provides": "PLATFORM"
    },
    {
      "id": "gig_economy",
      "name": "Gig Economy",
      "tier": 1,
      "sector": "INFRA",
      "cost_software": 8,
      "cost_hardware": 0,
      "revenue": 3,
      "valuation": 2,
      "maint_software": 1,
      "maint_hardware": 0,
      "requires": [],
      "provides": "PLATFORM"
    },
    {
      "id": "app_store",
      "name": "App Store",
      "tier": 1,
      "sector": "INFRA",
      "cost_software": 6,
      "cost_hardware": 0,
      "revenue": 4,
      "valuation": 3,
      "maint_software": 1,
      "maint_hardware": 0,
      "requires": [],
      "provides": "PLATFORM"
    },
    {
      "id": "indie_game_hit",
      "name": "Indie Game Hit",
      "tier": 1,
      "sector": "CONSUMER",
      "cost_software": 6,
      "cost_hardware": 0,
      "revenue": 3,
      "valuation": 1,
      "maint_software": 1,
      "maint_hardware": 0,
      "requires": [],
      "provides": "APP",
      "expansion": true
    },
    {
      "id": "news_aggregator",
      "name": "News Aggregator",
      "tier": 1,
      "sector": "CONSUMER",
      "cost_software": 4,
      "cost_hardware": 0,
      "revenue": 1,
      "valuation": 3,
      "maint_software": 1,
      "maint_hardware": 0,
      "requires": [],
      "provides": "PLATFORM",
      "expansion": true
    },
    {
      "id": "crowdfunding_page",
      "name": "Crowdfunding Page",
      "tier": 1,
      "sector": "FINTECH",
      "cost_software": 4,
      "cost_hardware": 0,
      "revenue": 1,
      "valuation": 3,
      "maint_software": 1,
      "maint_hardware": 0,
      "requires": [],
      "provides": "PLATFORM",
      "expansion": true
    },
    {
      "id": "budgeting_app",
      "name": "Budgeting App",
      "tier": 1,
      "sector": "FINTECH",
      "cost_software": 4,
      "cost_hardware": 0,
      "revenue": 2,
      "valuation": 1,
      "maint_software": 1,
      "maint_hardware": 0,
      "requires": [],
      "provides": "APP",
      "expansion": true
    },
    {
      "id": "smart_toy",
      "name": "Smart Toy",
      "tier": 1,
      "sector": "DEEP_TECH",
      "cost_software": 1,
      "cost_hardware": 3,
      "revenue": 2,
      "valuation": 2,
      "maint_software": 0,
      "maint_hardware": 1,
      "requires": [],
      "provides": "DEVICE",
      "expansion": true
    },
    {
      "id": "pet_tracker",
      "name": "Pet Tracker",
      "tier": 1,
      "sector": "DEEP_TECH",
      "cost_software": 2,
      "cost_hardware": 4,
      "revenue": 2,
      "valuation": 3,
      "maint_software": 0,
      "maint_hardware": 1,
      "requires": [],
      "provides": "IOT",
      "expansion": true
    },
    {
      "id": "sleep_monitor",
      "name": "Sleep Monitor",
      "tier": 1,
      "sector": "LIFE_SCI",
      "cost_software": 2,
      "cost_hardware": 4,
      "revenue": 1,
      "valuation": 4,
      "maint_software": 0,
      "maint_hardware": 1,
      "requires": [],
      "provides": "DATA",
      "expansion": true
    },
    {
      "id": "meditation_app",
      "name": "Meditation App",
      "tier": 1,
      "sector": "LIFE_SCI",
      "cost_software": 4,
      "cost_hardware": 0,
      "revenue": 1,
      "valuation": 2,
      "maint_software": 1,
      "maint_hardware": 0,
      "requires": [],
      "provides": "DATA",
      "expansion": true
    },
    {
      "id": "vpn_service",
      "name": "VPN Service",
      "tier": 1,
      "sector": "INFRA",
      "cost_software": 4,
      "cost_hardware": 0,
      "revenue": 2,
      "valuation": 2,
      "maint_software": 1,
      "maint_hardware": 0,
      "requires": [],
      "provides": "PLATFORM",
      "expansion": true
    },
    {
      "id": "dev_tools",
      "name": "Dev Tools",
      "tier": 1,
      "sector": "INFRA",
      "cost_software": 6,
      "cost_hardware": 0,
      "revenue": 3,
      "valuation": 2,
      "maint_software": 1,
      "maint_hardware": 0,
      "requires": [],
      "provides": "PLATFORM",
      "expansion": true
    }
  ]
}
